xmltree/__init__.py
xmltree/__main__.py
xmltree/cli.py
xmltree/config.py
xmltree/core.py
xmltree/logger.py
xmltree-0.1.1.dist-info/METADATA
xmltree-0.1.1.dist-info/WHEEL
xmltree-0.1.1.dist-info/entry_points.txt
xmltree-0.1.1.dist-info/licenses/LICENSE
xmltree-0.1.1.dist-info/RECORD
