Metadata-Version: 2.4
Name: xmltree
Version: 0.1.1
Summary: Full file(content) tree → XML
Project-URL: Homepage, https://github.com/adriangalilea/xmltree
Project-URL: Repository, https://github.com/adriangalilea/xmltree
Project-URL: Issues, https://github.com/adriangalilea/xmltree/issues
Author-email: Adrian Galilea <adriangalilea@gmail.com>
License: MIT
License-File: LICENSE
Keywords: converter,directory,filesystem,serialization,tree,xml
Classifier: Development Status :: 4 - Beta
Classifier: Intended Audience :: Developers
Classifier: License :: OSI Approved :: MIT License
Classifier: Operating System :: OS Independent
Classifier: Programming Language :: Python :: 3
Classifier: Programming Language :: Python :: 3.12
Classifier: Programming Language :: Python :: 3.13
Classifier: Topic :: Software Development :: Libraries
Classifier: Topic :: System :: Filesystems
Classifier: Topic :: Text Processing :: Markup :: XML
Classifier: Typing :: Typed
Requires-Python: >=3.12
Requires-Dist: pydantic-settings>=2.0
Requires-Dist: rich>=13.0
Requires-Dist: typer>=0.16.0
